myFramework/__init__.py
myFramework/api.py
myFramework/constants.py
myFramework/middleware.py
myFramework/response.py
myFramework-0.0.2.dist-info/METADATA
myFramework-0.0.2.dist-info/WHEEL
myFramework-0.0.2.dist-info/top_level.txt
myFramework-0.0.2.dist-info/RECORD
