Metadata-Version: 2.1
Name: myFramework
Version: 0.0.2
Summary: Python Web Framework to build APIs
Home-page: UNKNOWN
Author: Pablo Ruiz
Author-email: pabloruizruiz10@gmail.com
License: MIT
Platform: UNKNOWN
Classifier: Programming Language :: Python :: 3.9
Requires-Python: >=3.9.0
Requires-Dist: Jinja2 (==2.10.3)
Requires-Dist: parse (==1.12.1)
Requires-Dist: requests (==2.22.0)
Requires-Dist: requests-wsgi-adapter (==0.4.1)
Requires-Dist: WebOb (==1.8.5)
Requires-Dist: whitenoise (==4.1.4)
